Workbook

Sheet Summary Sheet
B2: Medivation Bio Private Limited | J2: Medivation Bio Private Limited
B3: Management_Report_(Funds Utilization Sheet)_upto_20th_July_2026 | J3: Management_Report_(Funds Utilization Sheet)_upto_30th_November_2025
B5: Particulars | C5: Ref | D5: Amount | E5: Particulars | F5: Ref | G5: Amount | J5: Particulars | K5: RAJ | L5: JAM | M5: Particulars | N5: RAJ | O5: JAM
B6: Utilization of Funds | E6: Sources of Funds | J6: Utilization of Funds | M6: Sources of Funds
B8: Capital Expenditure | E8: Promoters | J8: Capital Expenditure | M8: Promoters
B9: -----Furniture | C9: A | D9: =A!E21 -> 5783888.6 | E9: -------Parv Goyal | F9: K | G9: =L!E27 -> 3215000 | J9: -----Furniture | M9: -------Parv Goyal | N9: 0 | O9: 3215000
B10: -----Machinery | C10: B | D10: =B!E223 -> 3.8401272e+08 | E10: -------Ankit Bansal | F10: K | G10: =L!E46 -> 64825000 | J10: -----Machinery | M10: -------Ankit Bansal | N10: 0 | O10: 64825000
B11: -----Plant Land and Govt. Charges | C11: C | D11: ='C'!E11 -> 29301905 | E11: -------Aathesh Ventures Pvt Ltd | F11: K | G11: =L!E159 -> 322750000 | J11: -----Plant Land and Govt. Charges | M11: -------Aathesh Ventures Pvt Ltd | N11: 0 | O11: 204050000
B12: -----Office Equipment | C12: D | D12: =D!E40 -> 1678386.9 | E12: -------Divya Chadha | F12: K | G12: =L!E57 -> 3001000 | J12: -----Office Equipment | M12: -------Divya Chadha | N12: 0 | O12: 3001000
B13: -----Computer and Laptop | C13: E | D13: =E!E14 -> 721959.47 | E13: -------Share capital Introduced | F13: - | G13: 100000 | J13: -----Computer and Laptop | M13: -------Share capital Introduced | N13: 100000 | O13: 0
B14: -----Building Construction | C14: F | D14: =F!E167 -> 22192115
B15: -----Electrical Equipment | C15: N | D15: =N!E20 -> 14553723
B16: -----Intangible Asset | C16: - | D16: 229500
B17: -----Capital Work in Process | C17: - | D17: 76717813
B18: -----Fixed Asset of Rajasathan | C18: - | D18: =5466669.46 -> 5466669.5
B19: -----Sale Interstate Rajasthan | C19: - | D19: -2571905
B21: Account Payables | E21: Loan/WC from Bank
B22: -----Advance to Supplier | C22: H | D22: =H!C57 -> 18784302 | E22: ------HDFC Bank ( Loan -99649763 ) | F22: K | G22: =L!E210 -> 315990855
B23: -----Vendor Outstanding | C23: H1 | D23: ='H1'!C62 -> -20347708 | E23: ------HDFC WC Term Loan O/S | F23: - | G23: -4490
J24: Account Payables | M24: Interest Income
J25: -----Advance to Supplier | K25: 0 | L25: 54657320 | M25: -----FD Interest
B26: Operating Expenditure | E26: Interest Income | J26: -----Vendor Outstanding | K26: 0 | L26: -6279020 | M26: -----Misc Income | N26: 1741
B27: -----Salaries & Wages Due for the Month of June'26 | C27: - | D27: -99242 | E27: -----FD Interest | F27: - | G27: 3234701
B28: -----Other Expense(Jammu) | C28: I | D28: =I!C143 -> 37913501 | E28: -----Misc Income | F28: - | G28: =6177+1741+9404.8+94.4 -> 17417.2
B29: -----Other Expense(Rajasthan) | C29: I1 | D29: ='I1'!C94 -> 21223617 | J29: Operating Expenditure | M29: Cash Payment to Vendor
B30: -----Others | C30: J | D30: =J!D17 -> 2578582.8 | J30: -----Salaries & Wages Due for the Month of Nov'25 | L30: -1342841 | M30: -----Cash Introduce and Vendors Payment | N30: -14391
B31: -----CWIP Expense (Rajasthan) | C31: - | D31: -20375458 | J31: -----Other Expense(Jammu) | K31: 0 | L31: =40757772.43-45892.59 -> 40711880
B33: Raw Material Stock | E33: Cash Payment to Vendor | J33: -----Other Expense(Rajasthan) | K33: =20996305.25-74787.76 -> 20921517
B34: -----Raw Material-Stock | C34: G | D34: =G!C19 -> 28162669 | E34: -----Cash Introduce and Vendors Payment | F34: M | G34: =M!G16 -> 8483.09 | J34: -----Others | K34: 1000 | L34: =-184097+319483-(37243-285556-56250) -> 439949
B36: Duties and Taxes | J36: -----CWIP-Other Expense | K36: -20192877
B37: -----GST Input Jammu | C37: - | D37: 59061713
B38: -----GST Input Rajasthan | C38: - | D38: =750805.25-1500 -> 749305.25
B39: -----Other | C39: J | D39: =J!D6 -> 446.26
J40: Duties and Taxes
B41: Balance Available in Bank | J41: -----GST Input | K41: =729291.76-1500 -> 727791.76
B42: -----FD with HDFC Bank | C42: - | D42: 42633627 | J42: -----Other Receivables
B43: -----Balance in HDFC A/c- 99965 | C43: - | D43: =2622918.45-1116073 -> 1506845.5
B44: -----Balance in HDFC A/c - 7342 | C44: - | D44: 3251874 | J44: Balance Available in Bank
J45: -----FD with HDFC Bank (New)
B46: Suspense Entries | C46: K | D46: =K!C5 -> 0 | J46: -----Balance in HDFC A/c- 99965
J47: -----Balance in HDFC A/c - 7342
B48: Total | D48: =SUM(D6:D46) -> 7.1313085e+08 | E48: Total | G48: =SUM(G6:G46) -> 7.1313797e+08
J49: Suspense Entries
B50: Unreconciled Entries | C50: - | D50: =G48-D48 -> 7116.81 | G50: 0
J51: Total | L51: =K50+L50 -> 0 | M51: =SUM(M6:M49) -> 0 | O51: =N50+O50 -> 0
B52: Grand Total | D52: =D48+D50 -> 7.1313797e+08 | E52: Grand Total | G52: =G48 -> 7.1313797e+08
J53: Unreconciled Entries | K53: - | L53: =O51-L51 -> 0 | O53: 0
J55: Grand Total | L55: =L51+L53 -> 0 | M55: Grand Total | O55: =O51 -> 0

Sheet A
B2: Furniture
B4: Date | C4: PARTICULARS | D4: Nature | E4: Amount
B5: 45561 | C5: NEW LOOOK FURNITURE INDUSTRY | D5: Office Furniture | E5: 53389.82
B6: 45820 | C6: NEW LOOOK FURNITURE INDUSTRY | D6: Office Furniture | E6: 29661.02
B7: 46192 | C7: NEW LOOOK FURNITURE INDUSTRY | D7: Office Furniture | E7: 29661.02
B8: 45654 | C8: MAGNUS KLEANTECH | D8: Plant Furniture | E8: 1086000
B9: 45654 | C9: MAGNUS KLEANTECH | D9: Plant Furniture | E9: 988550
B10: 45709 | C10: MAGNUS KLEANTECH | D10: Plant Furniture | E10: 364729.68
B11: 45743 | C11: MAGNUS KLEANTECH | D11: Plant Furniture | E11: 315554.4
B12: 45743 | C12: MAGNUS KLEANTECH | D12: Plant Furniture | E12: 370717.2
B13: 45855 | C13: RS CUBE PROJECTS PRIVATE LIMITED | D13: Plant Furniture | E13: 291070.42
B14: 45907 | C14: MAGNUS KLEANTECH | D14: Plant Furniture | E14: 358372
B15: 45907 | C15: MAGNUS KLEANTECH | D15: Plant Furniture | E15: 735098
B16: 45912 | C16: Brij Industries | D16: Plant Furniture | E16: 805085
... B19: 46151 | C19: MAGNUS KLEANTECH | D19: Plant Furniture | E19: 251000
C21: Total | E21: =SUM(E5:E19) -> 5783888.6

Sheet B
B2: Machinery
B4: Date | C4: Particulars | D4: Nature | E4: Amount
B5: 45405 | C5: Airwaves Projects Pvt. Ltd | D5: Machinery and Tools | E5: 213321.43
B6: 45407 | C6: Airwaves Projects Pvt. Ltd | D6: Machinery and Tools | E6: 1058198.4
B7: 45415 | C7: Airwaves Projects Pvt. Ltd | D7: Machinery and Tools | E7: 437838.24
B8: 45426 | C8: Khalsa Electric Co | D8: Machinery and Tools | E8: 12570.34
B9: 45428 | C9: Airwaves Projects Pvt. Ltd | D9: Machinery and Tools | E9: 692029.59
B10: 45430 | C10: Airwaves Projects Pvt. Ltd | D10: Machinery and Tools | E10: 786387
B11: 45443 | C11: Airwaves Projects Pvt. Ltd | D11: Machinery and Tools | E11: 14800
B12: 45456 | C12: GMP Technical Solutions Pvt Ltd | D12: Machinery and Tools | E12: 845371.9
B13: 45457 | C13: GMP Technical Solutions Pvt Ltd | D13: Machinery and Tools | E13: 642567.05
B14: 45457 | C14: GMP Technical Solutions Pvt Ltd | D14: Machinery and Tools | E14: 791035.25
B15: 45463 | C15: GMP Technical Solutions Pvt Ltd | D15: Machinery and Tools | E15: 822612.4
B16: 45467 | C16: GMP Technical Solutions Pvt Ltd | D16: Machinery and Tools | E16: 534640.9
... B221: 46214 | C221: Mep Contract and Services | D221: Machinery and Tools | E221: 638400
C223: Total | E223: =SUM(E5:E221) -> 3.8401272e+08

Sheet C
B2: Plant Land and Govt. Charges
B3: Date | C3: Particulars | D3: Nature | E3: Amount
B4: 45449 | C4: J & K SIDCO LTD 250 | D4: Govt. Charges | E4: 2071000
B5: 45492 | C5: J & K SIDCO LTD 250 | D5: Govt. Charges | E5: 105805
B6: 45492 | C6: J & K SIDCO LTD 250 | D6: Govt. Charges | E6: 200
B7: 45492 | C7: J & K SIDCO LTD 250 | D7: Govt. Charges | E7: 15000
B8: 45852 | C8: Director TTC Wing-Electrical Inspection Department | D8: Inspection Charges | E8: 9900
B9: 45017 | C9: Medivation-Rajsthan | D9: Jammu Land | E9: 27100000
C11: Total | E11: =SUM(E4:E9) -> 29301905

Sheet D
B1: Office Equipment
B3: Date | C3: Particulars | D3: Nature | E3: Amount
B4: 45311 | C4: Source Peripherals | D4: Office Equipment | E4: 33050.85
B5: 45398 | C5: Global Village | D5: Office Equipment | E5: 129244
B6: 45453 | C6: Maha Lakshmi Motors | D6: Office Equipment | E6: 48690.42
B7: 45581 | C7: Medivation-Rajsthan | D7: Office Equipment | E7: 1731405
B8: 45686 | C8: Maha Lakshmi Motors | D8: Office Equipment | E8: 13347.46
B9: 45689 | C9: Medivation-Rajsthan | D9: Office Equipment | E9: 840500
B10: 45689 | C10: Jammu Expense | D10: Office Equipment | E10: -2571905
B11: 45723 | C11: Clicktech Retail Private Limited | D11: Office Equipment | E11: 8473.73
B12: 45723 | C12: Dawntech Electronics Private Limited | D12: Office Equipment | E12: 26554.69
B13: 45723 | C13: Dawntech Electronics Private Limited | D13: Office Equipment | E13: 11601.69
B14: 45723 | C14: Retailez Private Limited | D14: Office Equipment | E14: 2372.03
B15: 45723 | C15: Retailez Private Limited | D15: Office Equipment | E15: 2541.53
... B38: 46158 | C38: Power Vista Technologies | D38: Office Equipment | E38: 352600
C40: Total | E40: =SUM(E4:E38) -> 1678386.9

Sheet E
B1: Computer and Laptop
B3: Date | C3: Particulars | D3: Nature | E3: Amount
B4: 45587 | C4: ELEGANT COMMUNICATIONS | D4: Computer and Laptop | E4: 71959.32
B5: 45729 | C5: SABHAYA COMPUTERS | D5: Computer and Laptop | E5: 92796.2
B6: 45729 | C6: SABHAYA COMPUTERS | D6: Computer and Laptop | E6: 152542.38
B7: 45738 | C7: SABHAYA COMPUTERS | D7: Computer and Laptop | E7: 101694.92
B8: 45821 | C8: SABHAYA COMPUTERS | D8: Computer and Laptop | E8: 73728.81
B9: 45865 | C9: SABHAYA COMPUTERS | D9: Computer and Laptop | E9: 77966.1
B10: 46177 | C10: Quantum Technologies | D10: Computer and Laptop | E10: 50848
B11: 46106 | C11: Quantum Technologies | D11: Computer and Laptop | E11: 66949.16
B12: 46106 | C12: Quantum Technologies | D12: Computer and Laptop | E12: 33474.58
C14: Total | E14: =SUM(E4:E12) -> 721959.47

Sheet F
B2: Building Construction
B4: Air Conditioner
B5: Date | C5: Particulars | D5: Nature | E5: Amount
B6: 45437 | C6: Bahu Electronics | D6: Air Conditioner | E6: 28522.25
B7: 45558 | C7: AGGARWAL AGENCIES | D7: Air Conditioner | E7: 44531.25
B8: 45581 | C8: Tempcon Air Systems | D8: Air Conditioner | E8: 474317.19
B9: 45793 | C9: AGGARWAL AGENCIES | D9: Air Conditioner | E9: 575500
B10: 45815 | C10: PRECISION SYSTEMS | D10: Air Conditioner | E10: 334080
B11: 45818 | C11: AGGARWAL AGENCIES | D11: Air Conditioner | E11: 44531.25
B12: 45835 | C12: PRECISION SYSTEMS | D12: Air Conditioner | E12: 112666.4
C14: Total | E14: =SUM(E6:E12) -> 1614148.3
B16: Asset-Lal Sai
B17: Date | C17: Particulars | D17: Nature | E17: Amount
B18: 45311 | C18: Lal Sai Steel | D18: Assets- Lal Sai | E18: 1287300
B19: 45312 | C19: Lal Sai Steel | D19: Assets- Lal Sai | E19: 623329.66
B20: 45322 | C20: Lal Sai Steel | D20: Assets- Lal Sai | E20: 87082.2
B21: 45355 | C21: Lal Sai Steel | D21: Assets- Lal Sai | E21: 1222115.2
B22: 45384 | C22: Lal Sai Steel | D22: Assets- Lal Sai | E22: 465800
B23: 45385 | C23: Lal Sai Steel | D23: Assets- Lal Sai | E23: 483384.75
B24: 45386 | C24: Lal Sai Steel | D24: Assets- Lal Sai | E24: 234018.64
B25: 45442 | C25: Lal Sai Steel | D25: Assets- Lal Sai | E25: 70435.59
B26: 45447 | C26: Lal Sai Steel | D26: Assets- Lal Sai | E26: 38203.39
B27: 45448 | C27: Lal Sai Steel | D27: Assets- Lal Sai | E27: 54166.95
B28: 45478 | C28: Lal Sai Steel | D28: Assets- Lal Sai | E28: 2029443.2
B29: 45478 | C29: Lal Sai Steel | D29: Assets- Lal Sai | E29: 638820.34
... B39: 45943 | C39: Lal Sai Steel | D39: Assets- Lal Sai | E39: 383400
C41: Total | E41: =SUM(E18:E39) -> 11604471
B43: Building Construction
B44: Date | C44: Particulars | D44: Nature | E44: Amount
B45: 45423 | C45: Rishil Marble | D45: Building Construction | E45: 239160
B46: 45426 | C46: Davinder Iron & Steel Co. | D46: Building Construction | E46: 8561.86
B47: 45427 | C47: Aone Metal Industries | D47: Building Construction | E47: 1553.39
B48: 45427 | C48: Metal Dreams Industries | D48: Building Construction | E48: 8801.69
B49: 45428 | C49: Lalotra Sales Corporation | D49: Building Construction | E49: 1094.92
B50: 45444 | C50: K R Enterprises | D50: Building Construction | E50: 95409.33
B51: 45451 | C51: K R Enterprises | D51: Building Construction | E51: 45861.86
B52: 45453 | C52: K R Enterprises | D52: Building Construction | E52: 9806.78
B53: 45453 | C53: K R Enterprises | D53: Building Construction | E53: -8883.05
B54: 45454 | C54: Rishil Marble | D54: Building Construction | E54: 190380
B55: 45456 | C55: Delhi Building Material Corporation | D55: Building Construction | E55: 4883.9
B56: 45472 | C56: Delhi Building Material Corporation | D56: Building Construction | E56: 357828.81
... B136: 46181 | C136: M/S Indian Builder | D136: Building Construction | E136: 3457.64
C138: Total | E138: =SUM(E45:E136) -> 7087423
B140: Building Construction-Material
B141: Date | C141: Particulars | D141: Nature | E141: Amount
B142: 45864 | C142: Balaji Traders | D142: Building Construction-Material | E142: 91735
B143: 45982 | C143: Balaji Traders | D143: Building Construction-Material | E143: 36252.04
B144: 46002 | C144: Balaji Traders | D144: Building Construction-Material | E144: 36080
C146: Total | E146: =SUM(E142:E145) -> 164067.04
B148: TOUGHENED GLASS (SFT )
B149: Date | C149: Particulars | D149: Nature | E149: Amount
B150: 46220 | C150: Shakti Industries Unit-Ii | D150: TOUGHENED GLASS (SFT ) | E150: 445486.45
C152: Total | E152: =SUM(E150) -> 445486.45
B155: UPVC DOOR WINDOWS
B156: Date | C156: Particulars | D156: Nature | E156: Amount
B157: 45527 | C157: MR WINDOW | D157: UPVC DOOR WINDOWS | E157: 294350
B158: 45532 | C158: MR WINDOW | D158: UPVC DOOR WINDOWS | E158: 253750
B159: 45534 | C159: MR WINDOW | D159: UPVC DOOR WINDOWS | E159: 233450
B160: 45570 | C160: MR WINDOW | D160: UPVC DOOR WINDOWS | E160: 192850
B161: 45682 | C161: MR WINDOW | D161: UPVC DOOR WINDOWS | E161: 127118.64
B162: 45682 | C162: MR WINDOW | D162: UPVC DOOR WINDOWS | E162: 175000
C164: Total | E164: =SUM(E157:E162) -> 1276518.6
C167: Grand Total | E167: =E164+E152+E146+E41+E14+E138 -> 22192115

Sheet N
B1: -----Electrical Equipment
B3: Date | C3: Particulars | D3: Nature | E3: Amount
B4: 45579 | C4: N.T Electricals | D4: Electrical Equipment | E4: 3212475
B5: 45585 | C5: N.T Electricals | D5: Electrical Equipment | E5: 1525240
B6: 45631 | C6: N.T Electricals | D6: Electrical Equipment | E6: 573250
B7: 45631 | C7: N.T Electricals | D7: Electrical Equipment | E7: 2500000
B8: 45642 | C8: N.T Electricals | D8: Electrical Equipment | E8: 289750
B9: 45660 | C9: N.T Electricals | D9: Electrical Equipment | E9: 1334500
B10: 45668 | C10: N.T Electricals | D10: Electrical Equipment | E10: 2376500
B11: 45717 | C11: N.T Electricals | D11: Electrical Equipment | E11: 294700
B12: 45726 | C12: N.T Electricals | D12: Electrical Equipment | E12: 40000
B13: 45732 | C13: N.T Electricals | D13: Electrical Equipment | E13: 127400
B14: 45814 | C14: N.T Electricals | D14: Electrical Equipment | E14: 219625
B15: 45845 | C15: N.T Electricals | D15: Electrical Equipment | E15: 15000
... B18: 46118 | C18: N.T Electricals | D18: Electrical Equipment | E18: 268615
C20: Total | E20: =SUM(E4:E18) -> 14553723

Sheet G
B1: Raw Material
B3: Particular | C3: Amount
B4: Purchase Accounts | C4: =SUM(C5:C10) -> 6756337.7
B5: Local Purchase@18% | C5: 2389549.5
B6: Local Purchase@5% | C6: 137280
B7: Local Purchase @5% IGST | C7: 262240
B8: Purchase Discount Received | C8: -15674
B9: Purchase IGST @18% | C9: 3978742.2
B10: Purchase – Medical Consumables | C10: 4200
B12: Direct Expenses | C12: =SUM(C13:C17) -> 21406331
B13: Packaging Material | C13: 196694.45
B14: Raw Material | C14: 21062783
B15: Consumable Itmes 18% | C15: 112455.77
B16: Consumable Itmes 5% | C16: 30400
B17: Medical Items | C17: 3998.07
B19: Grand Total | C19: =C12+C4 -> 28162669

Sheet H
B1: Advance to Supplier
B3: Particulars | C3: Amount
B4: Air India-Baroda | C4: 23962
B5: Air India - Gurgaon | C5: 20278
B6: Tyco Electronics Middle East Fze | C6: 619234.93
B7: Magnus Kleantech | C7: 612313.49
B8: RS Cube Projects Private Limited | C8: 120169
B9: AS . Enterprises | C9: 1131500
B10: Ashish Enterprises | C10: 1924280
B11: BHAGWATI ENTERPRISES | C11: 5500
B12: COFFEE DAY GLOBAL LIMITED | C12: 26000
B13: Cost 2 Cost Computer | C13: 58700
B14: Country Inn & Suites (Radisson) Hotel | C14: 9104
B15: DHL- Express Pvt Ltd - Courier Service | C15: 549.01
... B55: Uber India System Pvt Ltd | C55: 731.37
B57: Grand Total | C57: =SUM(C4:C55) -> 18784302
C63: Debit | D63: Credit
B64: Other Creditors | C64: 44240 | D64: 287711.67
B65: Air India-Baroda | C65: 23962
B66: Air India - Gurgaon | C66: 20278
B67: Air India Limited-Delhi | D67: 21958
B68: Air India Limited -Kerala | D68: 18785.3
B69: Interglobe Aviation Limited ( Jammu ) | D69: 108911
B70: Interglobe Aviation Limited-Mumbai | D70: 7331.1
B71: Interglobe Aviation Limited ( New Delhi ) | D71: 95734.25
B72: Make My Trip (India) Pvt. Ltd.- Gurgaon | D72: 4562.02
B73: National Aviation Company of India Ltd -Jammu | D73: 14638
B74: Spicejet Limited | D74: 15792
B75: Amazon Creditors
B76: Foreign Creditors | C76: 619234.93 | D76: 3165021.9
B77: Allied Way (Hk) Limited | D77: 2502531.5
B78: BlockWise Enginnering LLC_x000D_ | D78: 2975.91
B79: Resonetics Medelec | D79: 346098.14
B80: Shanghai INT Medical Instruments Co., Ltd | D80: 313416.35
B81: Tyco Electronics Middle East Fze | C81: 619234.93
B82: Furniture Creditors | C82: 732482.49
B83: Magnus Kleantech | C83: 612313.49
B84: RS Cube Projects Private Limited | C84: 120169
B85: Insurance Creditors | D85: 20798.68
B86: ICICI Lombard General Insurance | D86: 20798.68
B87: Machinery Creditors | C87: 1131500 | D87: 3528240.5
B88: Airwaves Projects Pvt. Ltd | D88: 2925213
B89: AS . Enterprises | C89: 1131500
B90: Atul Traders | D90: 13000
B91: DPS Technology | D91: 122602.37
B92: GDI Engineers India ( Regd ) | D92: 10030
B93: PCI Analytics Private Limited | D93: 211974
B94: Rising Sun Enterprises | D94: 244123.15
B95: Sterile Safequip And Chemicals LLP | D95: 1298
B96: Rent for Creditors
B97: Alliance Tooling | D97: 148106
B98: Amisha Vinyls Pvt Ltd | D98: 280.25
B99: Anziam Bio Private Limited | D99: 44100
B100: Ashish Enterprises | C100: 1924280
B101: Baalay Safety Solutions | D101: 91996
B102: BHAGWATI ENTERPRISES | C102: 5500
B103: Bohra Agri Film Pvt. Ltd. | D103: 2076.8
B104: Chinar Roadlines (Regd.) | D104: 12415
B105: COFFEE DAY GLOBAL LIMITED | C105: 26000
B106: Cost 2 Cost Computer | C106: 58700
B107: Country Inn & Suites (Radisson) Hotel | C107: 9104
B108: DHL Express (India) Pvt Ltd- Import | D108: 94040.67
B109: DHL- Express Pvt Ltd - Courier Service | C109: 549.01
B110: Dn Printex Private Limited | D110: 473525
B111: Fedex Express Transportation And Suppy Chain Service (India) Pvt .Ltd. | D111: 2967
B112: Forbes Automation Technologies Pvt Ltd | C112: 1787500
B113: Friends Medicure Private Limited | D113: 188454
B114: Globalflow Logistics India Private Limited | C114: 988826
B115: Global Quality Services | C115: 17700
B116: Global Village | D116: 31860.48
B117: GMP Technical Solutions Pvt Ltd | D117: 2983091.1
B118: Gs1 India | C118: 23779.8
B119: Hdfc Commission | D119: 172040.51
B120: Hemetek Techno Instruments Pvt. Ltd. | D120: 376200
B121: Hilo Technologies | D121: 62761.78
B122: HOTEL BHOLA | D122: 9528.75
B123: HOTEL CORPORATE | C123: 40000
B124: IB Monotaro Private Limited | C124: 14670
B125: IHA Drug and Consumable | C125: 55900
B126: Impressions Printing & Packaging Limited Jammu Unit-Ii | D126: 144144
B127: Indian Packaging Machine | C127: 850000
B128: Jagdamba Electricals | D128: 2560.6
B129: Jhelum Resorts Pvt Limited | D129: 79231.42
B130: JIANGYIN HONGMENG RUBBER PLASTIC PRODUCT CO., LTD | C130: 1770719
B131: J S T LAMINATORS PVT LTD | C131: 899.16
B132: Jw Marriott | C132: 6250.28
B133: KAILASH FILLING STATION | C133: 79935.24
B134: Kamla's Chemicals & Instrument | C134: 115574
B135: KAY SONS INDIA PVT LTD | C135: 28320
B136: Khalsa Electric Co | C136: 14000
B137: Kira Corporation | D137: 23628
B138: K R Enterprises | D138: 111483.8
B139: Krishnarpan Hospitality Private Limited | C139: 1953
B140: Lal Sai Steel | C140: 1461238.6
B141: Maa Constructions | C141: 2200000
B142: Magrax Enterprises Private Limited | C142: 225594.75
B143: Make My Trip ( New ) | C143: 448608.18
B144: Mep Contract and Services | D144: 3264182.6
B145: MR Window | D145: 156500
B146: M/s Bharati Airtel Ltd. | D146: 2221.28
...

Sheet H1
B1: Vendor Outstanding
B3: Particulars | C3: Amount
B4: Air India Limited-Delhi | C4: 21958
B5: Air India Limited -Kerala | C5: 18785.3
B6: Interglobe Aviation Limited ( Jammu ) | C6: 108911
B7: Interglobe Aviation Limited-Mumbai | C7: 7331.1
B8: Interglobe Aviation Limited ( New Delhi ) | C8: 95734.25
B9: Make My Trip (India) Pvt. Ltd.- Gurgaon | C9: 4562.02
B10: National Aviation Company of India Ltd -Jammu | C10: 14638
B11: Spicejet Limited | C11: 15792
B12: Allied Way (Hk) Limited | C12: 2502531.5
B13: BlockWise Enginnering LLC_x000D_ | C13: 2975.91
B14: Resonetics Medelec | C14: 346098.14
B15: Shanghai INT Medical Instruments Co., Ltd | C15: 313416.35
... B60: -----Rajasthan Creditors | C60: 50534.37
B62: TOTAL | C62: =-SUM(C4:C60) -> -20347708

Sheet I
B4: Particular | C4: Amount
B5: Administration | C5: =SUM(C6:C8) -> 153032.81
B6: ADMINISTRATION CHARGES | C6: 30104
B7: Printing and Stationery | C7: 30528.81
B8: Website Maintenance | C8: 92400
B10: Bank Guarantee Charges | C10: 9558
B11: BG Commission & Other Charges | C11: 9558
B13: Business Promotion | C13: =SUM(C14:C15) -> 103718.65
B14: MARSHALL EMBERTON || MS-EMBRN-2 | C14: 55667.8
B15: MARSHAL WILLEN BLK-BRS | C15: 48050.85
B17: Consumables & Supplies_x000D_ | C17: 224.42
B18: Decoration Items | C18: 224.42
B20: Financial Charges & Income_x000D_ | C20: =SUM(C21:C26) -> 6195047.6
B21: Bank Charges | C21: 22496.68
B22: Bank Charges- Commission ( On Import of Goods) | C22: 37040.44
B23: Bank Charges ( Make My Trip ) | C23: 6440
B24: Forex Gain/Loss | C24: -1278377.5
B25: Interest on Term Loan | C25: 7379055
B26: Pre Emi Interest Charge | C26: 28393
B28: Freight & Logistics_x000D_ | C28: =SUM(C29:C37) -> 2027144.1
B29: Bonded Storage | C29: 6354
B30: CLEARANCE CHARGES | C30: 35720
B31: COURIER SERVICE_x000D_ | C31: 436555.08
B32: DISBURSEMENT FEE ( DHL Import ) | C32: 7993.32
B33: Freight Inward Charges | C33: 674135.16
B34: Freight Outward Charges | C34: 6000
B35: IMPORT EXPORT DUTIES | C35: 13710.37
B36: SW SURCHARGE | C36: 93537
B37: Transportation Charges | C37: 753139.15
B39: Hotel Expenses | C39: =SUM(C40:C41) -> 151189.4
B40: Hotel Stay Charges | C40: 100655.59
B41: Hotel Stay Expense (NEW) | C41: 50533.81
B43: Insurance | C43: =SUM(C44:C46) -> 1982082.1
B44: Health Insurances | C44: 1652054.3
B45: Insurance | C45: 230288.8
B46: Property Insurance | C46: 99739
B48: Operating Expenses (Indirect)_x000D_ | C48: =SUM(C49:C70) -> 7213339.4
B49: Amazon Prime Membership | C49: 1499
B50: APPLICATION CHARGERS | C50: 16236
B51: Bills Not Yet Received | C51: 43220
B52: Electricity Expense | C52: 1005189.4
B53: GOOGLE WORKSPACE | C53: 63509.37
B54: Insurance ( In Transit ) | C54: 63277.48
B55: LinkedIn | C55: 27176.92
B56: Misc Expense | C56: 10955
B57: Office Expense Non GST | C57: 41976.23
B58: Office Expenses | C58: 283995.61
B59: Out of Pocket | C59: 8220.34
B60: Parking Charges | C60: 900
... B70: Wi-Fi Expense_x000D_ | C70: 24372.27
B72: Professional & Consultancy Fees_x000D_ | C72: =SUM(C73:C79) -> 2399256.3
B73: Accounting Services Fee | C73: 881679
B74: CERTIFICATION CHARGES_x000D_ | C74: 1682.32
B75: Content Writer Professional Fee | C75: 145478
B76: Dsc Charges | C76: 5500
B77: LEI Registration Fee | C77: 18250
B78: Professional Fee | C78: 908175
B79: Professional Fee GST | C79: 438492
B81: Registration & Renewal Charges | C81: =SUM(C82:C84) -> 24700
B82: GCP Annual Fee 2026-27 | C82: 9262.5
B83: GCP Annual Fee 2027-28 | C83: 12350
B84: GCP Annual Fee up to June 2028 | C84: 3087.5
B86: Salary Expenses | C86: 10796653
B87: Staff Salary Expenses | C87: 10796653
B89: Taxes & Statutory Charges_x000D_ | C89: =SUM(C90:C96) -> 1123333.9
B90: CUSTOMS DUTY | C90: 631664
B91: GST Late Fee | C91: 218
B92: HEALTH CESS | C92: 202653
B93: INCOME TAX | C93: 3016
B94: Interest on Late TDS | C94: 7073.5
B95: Pollution Control Committee | C95: 221188.86
B96: Statutory Fees | C96: 57520.56
B98: TRAVELLING EXPESNE_x000D_ | C98: 73509.85
B99: Travelling Expenses (MMT) | C99: 73509.85
B101: Other | C101: =SUM(C102:C141) -> 5660711.2
B102: Advertisement / Design Charges | C102: 98938.61
B103: Barcode Registration Fee | C103: 29000
B104: BNC Global-Reimbursement | C104: 17816
B105: Business Promotion Expenses | C105: 119850
B106: Calibration Charges | C106: 7450
B107: Creative Cloud Pro | C107: 100668
B108: Credit Card Charges | C108: 1902.47
B109: Credit Card Late Fee | C109: 2364.18
B110: Damages ( 14 B ) | C110: 2999
B111: DGFT Application Charges | C111: 3210
B112: ESIC | C112: 1589
B113: Gift Card (Amazon) | C113: 119200
... B141: Warehouse Charges | C141: 3822.03
B143: Grand Total | C143: =C101+C98+C89+C86+C81+C72+C48+C43+C39+C28+C20+C17+C13+C10+C5 -> 37913501

Sheet I1
B1: Particular | C1: Amount
B2: Administration | C2: =SUM(C3:C5) -> 14817.2
B3: Printing & stationery | C3: 7727
B4: Printing & stationery- 12% | C4: 1992.86
B5: Printing & stationery- 18% | C5: 5097.34
B7: Business Promotion | C7: =SUM(C8:C9) -> 42713.86
B8: Business Promotion | C8: 42713.86
B10: Consumables & Supplies | C10: =SUM(C11:C13) -> 29781.74
B11: CONSUMABLE 12% | C11: 3928.54
B12: Consumable Items | C12: 25853.2
B14: Financial Charges | C14: =SUM(C15:C19) -> 688465.85
B15: Bank Charges | C15: 19141.85
B16: CERTIFICATION CHARGES | C16: 10000
B17: Dsc Charges | C17: 5000
B18: ROC-Stamp Duty | C18: 654324
B20: Freight & Logistics | C20: =SUM(C21:C25) -> 205858.74
B21: Air Freight | C21: 116055
B22: Forex Gain/Loss | C22: 3707.74
B23: FREIGHT CHARGES | C23: 196
B24: Inward Expenses | C24: 900
B25: Transportation Expenes | C25: 85000
B27: Guest House Rent | C27: =SUM(C28:C30) -> 703282.36
B28: RENT EXPENSE | C28: 543282.36
B29: Rent Jummu Guest House | C29: 160000
B31: Hotel Expenses | C31: =SUM(C32:C32) -> 25219
B32: Hotel Stay Charges | C32: 25219
B34: Office Expenses | C34: =SUM(C35:C42) -> 312473.1
B35: Computer Mouse | C35: 7711.88
B36: Mi Tv Stick with Built In Chromecast | C36: 2541.53
B37: Office Expence 5% | C37: 10590.48
B38: Office Expense Non GST | C38: 51585.23
B39: Office Expenses | C39: 143398.18
B40: Office Expesne -12% | C40: 13644.64
B41: Office Expesne -GST | C41: 79568.96
B42: Pan Drive | C42: 3432.2
B44: Operating Expenses (Indirect) | C44: =SUM(C45:C69) -> 16378379
B45: Activation Charges | C45: 1000
B46: Adoptor | C46: 1178.72
B47: Amazon Prime (Yearly Membership) | C47: 1499
B48: Application Charges | C48: 77961.26
B49: Application Charges -Gst | C49: 127000
B50: Electricity Expense | C50: 35407
B51: Google Cloud | C51: 14133.38
B52: GOOGLE WORKSPACE | C52: 139908.41
B53: HOUSEKEEPING EXP | C53: 45970.01
B54: LEASE AND IMPORMENT | C54: 40000
B55: Licenses Fees | C55: 3011
B56: Membership Fee -GST | C56: 15000
... B69: Wi-Fi Expense | C69: 67596.64
B71: Professional & Consultancy Fees | C71: =SUM(C72:C76) -> 1231788
B72: Accounting Services Fee | C72: 540000
B73: Consultant Charges | C73: 40000
B74: Content Writer Professional Fee | C74: 110688
B75: Professional fees | C75: 178600
B76: Professional fees -GST | C76: 362500
B78: Taxes & Statutory Charges | C78: =SUM(C79:C82) -> 6449
B79: Income Tax Paid | C79: 1880
B80: Interest on Late TDS | C80: 1265
B81: TDS LATE FILING FEES 234E | C81: 3304
B83: Travelling Expenses | C83: =SUM(C84:C89) -> 1407456.8
B84: TRAVELLING EXPENCE COMMISSION GST 18% | C84: 1139.82
B85: TRAVELLING EXPENSE | C85: 452295.44
B86: TRAVELLING EXPENSE- Gst 5% | C86: =823579.74 -> 823579.74
B87: TRAVELLING EXPESNE COMM. | C87: 90309.26
B88: TRAVELLING EXPESNE- Gst 18% | C88: 8824.57
B89: VISA EXPENSES | C89: 31308
B91: Other Expense | C91: =182580.26+69139.74-74787.76 -> 176932.24
B94: Total | C94: =C83+C78+C71+C44+C34+C31+C27+C20+C14+C10+C7+C2+C91 -> 21223617

Sheet J
B2: Other Receivables
B3: Unit | C3: Particular | D3: Amount
B4: Jammu | C4: TDS on contractor | D4: 446.26
C6: Total | D6: =SUM(D4:D4) -> 446.26
B8: Others
B9: Unit | C9: Particular | D9: Amount
B10: Jammu | C10: Parv Goyal card | D10: 138128.13
B11: Jammu | C11: Parv Goyal Imprest | D11: -365579.96
B12: Jammu | C12: FD Interest Accrured | D12: 2398127
B13: Jammu | C13: Rent Security | D13: 190000
B14: RJ | C14: Secuity Deposit-wifi | D14: 1000
B15: Jammu | C15: TDS RECEVIBLES | D15: 216907.6
C17: Total | D17: =SUM(D10:D15) -> 2578582.8

Sheet K
A1: SUSPENSE ENTRIES
A3: Date | B3: Particulars | C3: Gross Total | D3: Remarks
B4: Nil
C5: =SUM(C4:C4) -> 0

Sheet L
B2: -------Parv Goyal
B3: Date | C3: Particulars | D3: Vch Type | E3: Debit | F3: Credit
B4: 44705 | C4: Kotak Mahindra Bank A/c 8545603885 | D4: Receipt | F4: 100000
B5: 44707 | C5: Kotak Mahindra Bank A/c 8545603885 | D5: Receipt | F5: 500000
B6: 44716 | C6: Kotak Mahindra Bank A/c 8545603885 | D6: Receipt | F6: 500000
B7: 44739 | C7: Kotak Mahindra Bank A/c 8545603885 | D7: Receipt | F7: 500000
B8: 44746 | C8: Kotak Mahindra Bank A/c 8545603885 | D8: Receipt | F8: 300000
B9: 44766 | C9: Kotak Mahindra Bank A/c 8545603885 | D9: Payment | E9: 25000
B10: 44769 | C10: Kotak Mahindra Bank A/c 8545603885 | D10: Receipt | F10: 500000
B11: 44774 | C11: Kotak Mahindra Bank A/c 8545603885 | D11: Receipt | F11: 500000
B12: 44795 | C12: Kotak Mahindra Bank A/c 8545603885 | D12: Receipt | F12: 500000
B13: 44795 | C13: Kotak Mahindra Bank A/c 8545603885 | D13: Receipt | F13: 500000
B14: 44831 | C14: Kotak Mahindra Bank A/c 8545603885 | D14: Payment | E14: 500000
B15: 44831 | C15: Kotak Mahindra Bank A/c 8545603885 | D15: Payment | E15: 500000
B16: 44832 | C16: Kotak Mahindra Bank A/c 8545603885 | D16: Payment | E16: 500000
B17: 44832 | C17: Kotak Mahindra Bank A/c 8545603885 | D17: Payment | E17: 500000
B18: 44833 | C18: Kotak Mahindra Bank A/c 8545603885 | D18: Payment | E18: 500000
B19: 44833 | C19: Kotak Mahindra Bank A/c 8545603885 | D19: Payment | E19: 500000
B20: 44833 | C20: Kotak Mahindra Bank A/c 8545603885 | D20: Payment | E20: 150000
B21: 44834 | C21: Kotak Mahindra Bank A/c 8545603885 | D21: Payment | E21: 500000
B22: 44879 | C22: HDFC BANK 99999999999965 | D22: Receipt | F22: 2500000
B23: 44879 | C23: HDFC BANK 99999999999965 | D23: Receipt | F23: 2490000
B24: 44883 | C24: HDFC BANK 99999999999965 | D24: Payment | E24: 2000000
C26: Total | E26: =SUM(E4:E25) -> 5675000 | F26: =SUM(F4:F25) -> 8890000
C27: Closing Balance | E27: =F26-E26 -> 3215000
B30: ------Ankit Bansal
B31: Date | C31: Particulars | D31: Vch Type | E31: Debit | F31: Credit
B32: 44287 | C32: Opening Balance | F32: 10000
B33: 45173 | C33: HDFC BANK 99999999999965 | D33: Receipt | F33: 10200000
B34: 45474 | C34: HDFC BANK 99999999999965 | D34: Receipt | F34: 5000000
B35: 45475 | C35: HDFC BANK 99999999999965 | D35: Receipt | F35: 5000000
B36: 45475 | C36: HDFC 50200098257342 | D36: Receipt | F36: 700000
B37: 45492 | C37: HDFC 50200098257342 | D37: Receipt | F37: 2000000
B38: 45547 | C38: HDFC BANK 99999999999965 | D38: Receipt | F38: 10000000
B39: 45565 | C39: HDFC BANK 99999999999965 | D39: Receipt | F39: 10000000
B40: 45632 | C40: HDFC BANK 99999999999965 | D40: Receipt | F40: 10000000
B41: 45679 | C41: HDFC BANK 99999999999965 | D41: Receipt | F41: 3000000
B42: 45686 | C42: HDFC BANK 99999999999965 | D42: Receipt | F42: 2315000
B43: 45848 | C43: HDFC BANK 99999999999965 | D43: Receipt | F43: 5000000
B44: 45936 | C44: HDFC BANK 99999999999965 | D44: Receipt | F44: 1600000
C45: Total | E45: =SUM(E32:E43) -> 0 | F45: =SUM(F32:F44) -> 64825000
C46: Closing Balance | E46: =F45-E45 -> 64825000
B49: ------Divya Chadha
B50: Date | C50: Particulars | D50: Vch Type | E50: Debit | F50: Credit
B51: 45495 | C51: HDFC BANK 99999999999965 | D51: Receipt | F51: 1000
B52: 45495 | C52: HDFC BANK 99999999999965 | D52: Receipt | F52: 1000000
B53: 45498 | C53: HDFC BANK 99999999999965 | D53: Receipt | F53: 1000000
B54: 45500 | C54: HDFC BANK 99999999999965 | D54: Receipt | F54: 1000000
C56: Total | E56: =SUM(E51:E55) -> 0 | F56: =SUM(F51:F55) -> 3001000
C57: Closing Balance | E57: =F56-E56 -> 3001000
B60: ------Aathesh Ventures Pvt Ltd
B61: Date | C61: Particulars | D61: Vch Type | E61: Debit | F61: Credit
B62: 44827 | C62: Kotak Mahindra Bank A/c 8545603885 | D62: Receipt | F62: 500000
B63: 44831 | C63: Kotak Mahindra Bank A/c 8545603885 | D63: Receipt | F63: 4000000
B64: 44835 | C64: Kotak Mahindra Bank A/c 8545603885 | D64: Receipt | F64: 1500000
B65: 44861 | C65: Kotak Mahindra Bank A/c 8545603885 | D65: Receipt | F65: 1000000
B66: 44880 | C66: HDFC BANK 99999999999965 | D66: Receipt | F66: 6000000
B67: 44881 | C67: HDFC BANK 99999999999965 | D67: Receipt | F67: 6000000
B68: 44886 | C68: HDFC BANK 99999999999965 | D68: Receipt | F68: 2000000
B69: 44902 | C69: HDFC BANK 99999999999965 | D69: Receipt | F69: 2000000
B70: 45162 | C70: HDFC BANK 99999999999965 | D70: Receipt | F70: 2500000
B71: 45180 | C71: HDFC BANK 99999999999965 | D71: Receipt | F71: 2200000
B72: 45190 | C72: HDFC BANK 99999999999965 | D72: Receipt | F72: 9000000
B73: 45202 | C73: HDFC BANK 99999999999965 | D73: Receipt | F73: 3000000
... B99: 45659 | C99: HDFC BANK 99999999999965 | D99: Receipt | F99: 2000000
B100: 45670 | C100: HDFC BANK 99999999999965 | D100: Payment | E100: 20750000
B101: 45684 | C101: HDFC BANK 99999999999965 | D101: Receipt | F101: 3000000
B102: 45694 | C102: HDFC BANK 99999999999965 | D102: Receipt | F102: 3000000
B103: 45713 | C103: HDFC BANK 99999999999965 | D103: Receipt | F103: 3000000
B104: 45716 | C104: HDFC BANK 99999999999965 | D104: Receipt | F104: 2000000
B105: 45719 | C105: HDFC BANK 99999999999965 | D105: Receipt | F105: 20000000
B106: 45736 | C106: HDFC BANK 99999999999965 | D106: Receipt | F106: 2000000
B107: 45745 | C107: HDFC BANK 99999999999965 | D107: Receipt | F107: 2000000
B108: 45749 | C108: HDFC BANK 99999999999965 | D108: Receipt | F108: 12000000
B109: 45772 | C109: HDFC BANK 99999999999965 | D109: Receipt | F109: 2500000
B110: 45778 | C110: HDFC BANK 99999999999965 | D110: Receipt | F110: 1000000
B111: 45798 | C111: HDFC BANK 99999999999965 | D111: Receipt | F111: 2000000
B112: 45806 | C112: HDFC BANK 99999999999965 | D112: Receipt | F112: 3000000
... B156: 46223 | C156: HDFC BANK 99999999999965 ( Gurugram ) | D156: Receipt | F156: 2500000
C158: Total | E158: =SUM(E62:E156) -> 20750000 | F158: =SUM(F62:F156) -> 343500000
C159: Closing Balance | E159: =F158-E158 -> 322750000
B161: ------HDFC TERM LOAN
B162: Date | C162: Particulars | D162: Vch Type | E162: Debit | F162: Credit
B163: 45477 | C163: HDFC WC TERM LOAN | D163: Journal | F163: 67290346
B164: 45488 | C164: HDFC WC TERM LOAN | D164: Journal | F164: 12693494
B165: 45492 | C165: HDFC WC TERM LOAN | D165: Journal | F165: 1438278
B166: 45493 | C166: HDFC WC TERM LOAN | D166: Journal | F166: 19920000
B167: 45503 | C167: HDFC WC TERM LOAN | D167: Journal | F167: 5553375
B168: 45537 | C168: HDFC WC TERM LOAN | D168: Journal | F168: 16591661
B169: 45554 | C169: HDFC WC TERM LOAN | D169: Journal | F169: 704850
B170: 45568 | C170: HDFC WC TERM LOAN | D170: Journal | F170: 13023090
B171: 45586 | C171: HDFC WC TERM LOAN | D171: Journal | F171: 2062703
B172: 45597 | C172: HDFC WC TERM LOAN | D172: Journal | F172: 2543330
B173: 45633 | C173: HDFC WC TERM LOAN | D173: Journal | F173: 18526647
B174: 45637 | C174: HDFC WC TERM LOAN | D174: Journal | F174: 4460103
... B189: 46045 | C189: HDFC WC TERM LOAN | D189: Journal | F189: 2435315
B190: 46060 | C190: HDFC WC TERM LOAN | D190: Journal | E190: 3088498
B191: 46088 | C191: HDFC WC TERM LOAN | D191: Journal | E191: 3158584
B192: 46092 | C192: HDFC WC TERM LOAN | D192: Journal | F192: 11094000
B193: 46099 | C193: HDFC WC TERM LOAN | D193: Journal | F193: 1838468
...

Sheet M
B2: List of Vendors/ Expeses paid through Cash but no cash withdrawl from Bank
B4: Date | C4: Particulars | D4: Vch Type | E4: Vch No. | F4: Debit | G4: Credit
B5: Closing Bal. | C5: Medivation Rajasthan | D5: Payment | E5: - | F5: 14391
B6: 45747 | C6: Parv Goyal imprest | D6: Journal | E6: - | F6: 10000
B7: 45748 | C7: Khalsa Electric Co | D7: Payment | E7: - | G7: 14833
B8: 45748 | C8: Khalsa Electric Co | D8: Payment | E8: - | G8: 10240
B9: 45873 | C9: Reliant Packaging Films Private Ltd | D9: Payment | E9: - | G9: 991
B10: 45912 | C10: Chinar Roadlines (Regd.) | D10: Payment | E10: - | G10: 46715
B11: 45934 | C11: TCI Freight | D11: Journal | E11: - | G11: 100
B12: 45957 | C12: VTrans (India) Limited | D12: Payment | E12: - | G12: 1614
B13: 46112 | C13: Parv Goyal imprest-II | D13: Journal | E13: - | F13: 41000
B14: 46112 | C14: Bombay Scientific Stores Pvt Ltd | D14: Journal | E14: - | F14: 618.91
C15: Total | F15: =SUM(F5:F14) -> 66009.91 | G15: =SUM(G5:G14) -> 74493
C16: Net Cash | G16: =G15-F15 -> 8483.09

Sheet F1(PARTY ADVANCE)
A3: Row Labels | B3: Sum of Amount
A4: Airwaves Project Private Limited | B4: 1820679
A5: AS Enterprise | B5: 1031500
A6: Ashish Enterprises | B6: 10467000
A7: Balay Safety Solutions | B7: 1924634
A8: BlockWise Enginnering LLC | B8: 153183.55
A9: BW TEC AG | B9: 47665746
A10: Controller Drug and food Control | B10: 12500
A11: Extrumed Inc Dba Vesta | B11: 729786.54
A12: Friends Medicure Pvt Ltd | B12: 9558 | C12: Bills received
A13: Kavita Gupta | B13: 20000 | C13: Trademark and copyright (Divya Mam)
A14: Lal Sai Steel | B14: 10658686 | C14: to be adjusted against bills
A15: Maa Constructions | B15: 2000000
A16: Machine Solutions INC | B16: 24156684
A17: MAGNUS KLEANTECH | B17: 2851442 | C17: bill received
A18: Maxwell Exports | B18: 2002000
A19: N T ELECRICALS | B19: 1965104 | C19: Bills received
A20: N.T.ELECTRICALS | B20: 7835574 | C20: Bills received
A21: Narola Machines | B21: 442500
A22: Niva Bupa Health Insurance | B22: 58551
A23: Parv Cardit Card | B23: 132655 | C23: to be expense off
A24: Pass Card Co Ltd | B24: 6961237.3
A25: PCI Pest Control Private Limited | B25: 29500
A26: Pentagon Assembly Automation Pvt Ltd | B26: 10000000
A27: RADIAINT INDUSTRIES | B27: 7200000
A28: RAJ ENTERPRISES | B28: 487627
A29: RESONETICS MEDELEC | B29: 1614122
A30: Rising Sun Enterprises | B30: 350734
A31: Safeway Technology | B31: 482800
A32: Samarth Electronices | B32: 29972
A33: Shibaura Machine India Pvt Ltd | B33: 11798500
A34: Spento Engineering | B34: 1152123
A35: STERILE SAFEQUIP AND CHEMICALS LLP | B35: 2920205 | C35: bill received
A36: The New India Assurance Co Ltd | B36: 52864
A37: ThermoLab Scientific Equipments Pvt Ltd | B37: 2053200 | C37: bill received
A38: Vesta Thermoplastics Divison | B38: 1556999.8
A39: ZEUS INDUSTRIAL PRODUTS | B39: 277340.09
A40: Grand Total | B40: =SUM(B3:B39) -> 1.6290501e+08
